{
  "data": [
    {
      "responsive_id": null,
      "user_id": 1,
      "issued_date": "12/13/2019",
      "course_name": "BioStatistics",
      "email": "roxyfloodgate@email.com",
      "service": "Software Development",
      "total": 3428,
      "avatar": "10-small.png",
      "invoice_status": "Paid",
      "balance": "724 KD",
      "due_date": "05/23/2021"
    },
    {
      "responsive_id": null,
      "user_id": 2,
      "issued_date": "12/13/2019",
      "course_name": "Cardiology Bundle I",
      "email": "tariqahmed@gmail.com",
      "service": "Software Development",
      "total": 400,
      "avatar": "9-small.png",
      "invoice_status": "Paid",
      "balance": "300 KD",
      "due_date": "04/23/2021"
    },
    {
      "responsive_id": null,
      "user_id": 3,
      "issued_date": "12/13/2019",
      "course_name": "Cardiology Bundle & ECG",
      "email": "doctorwho@gmail.com",
      "service": "Software Development",
      "total": 600,
      "avatar": "8-small.png",
      "invoice_status": "Paid",
      "balance": "500 KD",
      "due_date": "04/21/2021"
    },
    {
      "responsive_id": null,
      "user_id": 4,
      "issued_date": "12/13/2019",
      "course_name": "Pathology Bundle I",
      "email": "yasmin@gmail.com",
      "service": "Software Development",
      "total": 120,
      "avatar": "7-small.png",
      "invoice_status": "Paid",
      "balance": "100 KD",
      "due_date": "04/21/2021"
    },
    {
      "responsive_id": null,
      "user_id": 5,
      "issued_date": "12/13/2019",
      "course_name": "Pathology Bundle II",
      "email": "Jasmon@gmail.com",
      "service": "Software Development",
      "total": 230,
      "avatar": "6-small.png",
      "invoice_status": "Paid",
      "balance": "300 KD",
      "due_date": "04/21/2021"
    },
    {
      "responsive_id": null,
      "user_id": 6,
      "issued_date": "12/13/2019",
      "course_name": "Surgery in Adolesence",
      "email": "jane@gmail.com",
      "service": "Software Development",
      "total": 5000,
      "avatar": "5-small.png",
      "invoice_status": "Paid",
      "balance": "2500 KD",
      "due_date": "04/21/2021"
    }
  ]
}
